{
  "name" : "A. Vacations",
  "testType" : "SINGLE",
  "input" : {
    "type" : "STANDARD",
    "fileName" : "input.txt"
  },
  "output" : {
    "type" : "STANDARD",
    "fileName" : "output.txt"
  },
  "tests" : [ {
    "input" : "4\n1 3 2 0\n",
    "output" : "2\n",
    "index" : 0,
    "active" : true
  }, {
    "input" : "7\n1 3 3 2 1 2 3\n",
    "output" : "0\n",
    "index" : 1,
    "active" : true
  }, {
    "input" : "2\n2 2\n",
    "output" : "1\n",
    "index" : 2,
    "active" : true
  } ],
  "location" : "src/com/darkbit/problems",
  "vmArgs" : "-Xmx256M",
  "mainClass" : "Main",
  "taskClass" : "com.darkbit.problems.AVacations",
  "checkerClass" : "net.egork.chelper.checkers.TokenChecker",
  "checkerParameters" : "",
  "testClasses" : [ ],
  "date" : "2019.02.08",
  "contestName" : "Codeforces Round #363 (Div. 1)",
  "truncate" : true,
  "inputClass" : "net.egork.io.InputReader",
  "outputClass" : "net.egork.io.OutputWriter",
  "includeLocale" : false,
  "failOnOverflow" : true,
  "interactive" : false,
  "interactor" : "net.egork.chelper.tester.Interactor"
}